example/__init__.py
example/keras_gradients.py
example/keras_switch.py
example/layers_example.py
example/tf_loop.py
tool4keras/__init__.py
tool4keras/callbacks.py
tool4keras/embedding_base.py
tool4keras/embedding_pretrain.py
tool4keras/layers.py
tool4keras/loss.py
tool4keras/metrics.py
tool4keras/tokenizers.py
tool4keras/utils.py
tool4keras/utils_colab.py
tool4keras/util/__init__.py
tool4keras/util/focaloss.py
tool4keras/util/optimizerF1.py
tool4keras-0.0.1.dist-info/METADATA
tool4keras-0.0.1.dist-info/WHEEL
tool4keras-0.0.1.dist-info/top_level.txt
tool4keras-0.0.1.dist-info/RECORD
