Metadata-Version: 2.1
Name: tool4keras
Version: 0.0.1
Summary: collect common tool of keras
Home-page: UNKNOWN
Author: samma
Author-email: 13336502700@163.com
License: MIT
Platform: UNKNOWN
Requires: keras
Requires: google_drive_downloader
Requires: tensorflow
Requires: numpy
Requires: gensim
Requires: tqdm
